rest_marshmallow/__init__.py
django_rest_marshmallow-4.0.2.dist-info/LICENSE
django_rest_marshmallow-4.0.2.dist-info/METADATA
django_rest_marshmallow-4.0.2.dist-info/WHEEL
django_rest_marshmallow-4.0.2.dist-info/top_level.txt
django_rest_marshmallow-4.0.2.dist-info/RECORD
