Metadata-Version: 2.1
Name: django-rest-marshmallow
Version: 4.0.2
Summary: Marshmallow schemas for Django REST framework
Home-page: https://github.com/marshmallow-code/django-rest-marshmallow
Author: Tom Christie
Author-email: tom@tomchristie.com
Maintainer: Steven Loria
Maintainer-email: sloria1@gmail.com
License: BSD
Platform: UNKNOWN
Classifier: Development Status :: 4 - Beta
Classifier: Environment :: Web Environment
Classifier: Framework :: Django
Classifier: Intended Audience :: Developers
Classifier: License :: OSI Approved :: BSD License
Classifier: Operating System :: OS Independent
Classifier: Natural Language :: English
Classifier: Programming Language :: Python :: 2
Classifier: Programming Language :: Python :: 2.7
Classifier: Programming Language :: Python :: 3
Classifier: Programming Language :: Python :: 3.5
Classifier: Programming Language :: Python :: 3.6
Classifier: Topic :: Internet :: WWW/HTTP
